hnews/__init__.py
hnews/__main__.py
hnews/ask.py
hnews/explore.py
hnews/globals.py
hnews/jobs.py
hnews/news.py
hnews/test.py
hnews-0.0.1.dist-info/LICENSE
hnews-0.0.1.dist-info/METADATA
hnews-0.0.1.dist-info/WHEEL
hnews-0.0.1.dist-info/entry_points.txt
hnews-0.0.1.dist-info/top_level.txt
hnews-0.0.1.dist-info/RECORD
