Metadata-Version: 2.1
Name: hnews
Version: 0.0.1
Summary: CLI to browse content of HackerNews
Home-page: https://github.com/plant99/hackernews-cli
Author: plant99
Author-email: shivashispadhi@gmail.com
License: UNKNOWN
Platform: UNKNOWN
Classifier: Programming Language :: Python :: 3
Classifier: License :: OSI Approved :: MIT License
Classifier: Operating System :: OS Independent
